Workbook

Sheet 1.Исходные данные
A1: РГЗ «Организация нового производства (ТЭО)» — Вариант 31
A3: Параметр | B3: Значение | C3: Примечание
A4: МРОТ, р. | B4: 27093 | C4: задано преподавателем
A5: ДЗП (доп.з/п), % | B5: 0.15 | C5: табл.1, вариант 31
A6: Годовой объем выпуска, Q_А, шт | B6: 7500 | C6: табл.1
A7: Порог рентабельности, Пр_А, дн | B7: 180 | C7: табл.1
A8: Годовой объем выпуска, Q_Б, шт | B8: 3100 | C8: табл.1
A9: Порог рентабельности, Пр_Б, дн | B9: 180 | C9: табл.1
A10: НДС, % | B10: 0.22 | C10: п.2.6
A11: Ставка страховых взносов, % | B11: 0.3 | C11: п.2.6
A12: Ставка налога на прибыль, % | B12: 0.25 | C12: п.2.6
A13: Районный коэффициент Кр | B13: 1.25 | C13: п.6.2
A14: Число смен Ксм | B14: 2 | C14: п.2.6, двухсменный режим
A15: Продолжительность смены, ч | B15: 8 | C15: п.5.1
... A17: Коммерческие расходы, % от произв.с/с | B17: 0.15 | C17: п.7.1

Sheet 2.Табл.2 Техпроцесс
A1: № | B1: Операция | C1: Разряд | D1: t_А, н/ч | E1: t_Б, н/ч | F1: Квн | G1: Квыб | H1: альфа простоя,%
A2: 1 | B2: Станочная | C2: 4 | D2: 1.8 | E2: 2.5 | F2: 1.03 | G2: – | H2: 6
A3: 2 | B3: Слесарная | C3: 4 | D3: 2.4 | E3: 2.9 | F3: 1 | G3: – | H3: 6
A4: 3 | B4: Монтажно-сборочная | C4: 3 | D4: 4.3 | E4: 5 | F4: 1 | G4: – | H4: 0
A5: 4 | B5: Наладочная, регулировочная, испытательная | C5: 5 | D5: 6.5 | E5: 9.6 | F5: 1 | G5: – | H5: 0
A6: 5 | B6: Технический контроль качества | C6: 3 | D6: 0.5 | E6: 0.6 | F6: – | G6: 0.5 | H6: 0

Sheet 3.Табл.6 ФондВремени
A1: Таблица 6 — Расчет полезного фонда времени
A2: № | B2: Состав фонда времени | C2: Ед.изм. | D2: Количество | E2: Процент
A3: 1 | B3: Календарные дни | C3: Дни | D3: 365
A4: 2 | B4: Выходные и праздничные дни | C4: Дни | D4: 118
A5: 3 | B5: Рабочие дни (номинальный фонд времени) | C5: Дни | D5: =D3-D4 -> 247 | E5: 100
A6: 4.1 | B6: отпуска основные и дополнительные | C6: Дни | D6: =ROUND(D$5*6/100,0) -> 15 | E6: 6
A7: 4.2 | B7: учебные отпуска | C7: Дни | D7: =ROUND(D$5*0.6/100,0) -> 1 | E7: 0.6
A8: 4.3 | B8: отпуска по беременности и родам | C8: Дни | D8: =ROUND(D$5*0.6/100,0) -> 1 | E8: 0.6
A9: 4.4 | B9: выполнение гос.обязанностей | C9: Дни | D9: =ROUND(D$5*0.4/100,0) -> 1 | E9: 0.4
A10: 4.5 | B10: болезни | C10: Дни | D10: =ROUND(D$5*2.6/100,0) -> 6 | E10: 2.6
A11: 4 | B11: Целодневные невыходы, итого | C11: Дни | D11: =SUM(D6:D10) -> 24 | E11: 10.2
A12: 5 | B12: Явочное время | C12: Дни | D12: =D5-D11 -> 223
A13: 6 | B13: Средняя продолжительность рабочего дня | C13: Час | D13: 8
A14: 7 | B14: Полезный фонд времени (Фп) | C14: Час | D14: =D12*D13 -> 1784

Sheet 4.Табл5_ОборудПлощади
A1: Расчёт потребности в оборудовании, рабочих местах и площадях (п.5)
A3: Операция № | B3: Наименование | C3: α простоя,% | D3: Fд, час = Fном*tсм*Ксм*(1-α) | E3: Числитель Σ(Qj*tij) | F3: Квн | G3: Ср расч. | H3: Ср принято
A4: 1 | B4: Станочная | C4: 6 | D4: ='3.Табл.6 ФондВремени'!D5*'1.Исходные данные'!B15*'1.Исходные данные'!B14*(1-C4/100) -> 3714.88 | E4: ='1.Исходные данные'!B6*'2.Табл.2 Техпроцесс'!D2+'1.Исходные данные'!B8*'2.Табл.2 Техпроцесс'!E2 -> 21250 | F4: 1.03 | G4: =E4/(D4*F4) -> 5.5536297 | H4: =ROUND(G4,0) -> 6
A5: 2 | B5: Слесарная | C5: 6 | D5: ='3.Табл.6 ФондВремени'!D5*'1.Исходные данные'!B15*'1.Исходные данные'!B14*(1-C5/100) -> 3714.88 | E5: ='1.Исходные данные'!B6*'2.Табл.2 Техпроцесс'!D3+'1.Исходные данные'!B8*'2.Табл.2 Техпроцесс'!E3 -> 26990 | F5: 1 | G5: =E5/(D5*F5) -> 7.265376 | H5: =ROUND(G5,0) -> 7
A6: 3 | B6: Монтажно-сборочная | C6: 0 | D6: ='3.Табл.6 ФондВремени'!D5*'1.Исходные данные'!B15*'1.Исходные данные'!B14*(1-C6/100) -> 3952 | E6: ='1.Исходные данные'!B6*'2.Табл.2 Техпроцесс'!D4+'1.Исходные данные'!B8*'2.Табл.2 Техпроцесс'!E4 -> 47750 | F6: 1 | G6: =E6/(D6*F6) -> 12.08249 | H6: =ROUND(G6,0) -> 12
A7: 4 | B7: Наладочная | C7: 0 | D7: ='3.Табл.6 ФондВремени'!D5*'1.Исходные данные'!B15*'1.Исходные данные'!B14*(1-C7/100) -> 3952 | E7: ='1.Исходные данные'!B6*'2.Табл.2 Техпроцесс'!D5+'1.Исходные данные'!B8*'2.Табл.2 Техпроцесс'!E5 -> 78510 | F7: 1 | G7: =E7/(D7*F7) -> 19.865891 | H7: =ROUND(G7,0) -> 20
A8: 5 | B8: Технический контроль (контролёры, форм.9) | C8: 0 | D8: ='3.Табл.6 ФондВремени'!D14 -> 1784 | E8: ='1.Исходные данные'!B6*'2.Табл.2 Техпроцесс'!D6*'2.Табл.2 Техпроцесс'!G6+'1.Исходные данные'!B8*'2.Табл.2 Техпроцесс'!E6*'2.Табл.2 Техпроцесс'!G6 -> 2805 | F8: — | G8: =E8/D8 -> 1.5723094 | H8: =MAX(3,ROUND(G8,0)) -> 3
A10: Расчёт площадей
A11: Производственная площадь, м2 | B11: =20*'4.Табл5_ОборудПлощади'!H4+10*('4.Табл5_ОборудПлощади'!H5+'4.Табл5_ОборудПлощади'!H6+'4.Табл5_ОборудПлощади'!H7+'4.Табл5_ОборудПлощади'!H8) -> 540
A12: Площадь вспомог.помещений, м2 (заполняется по итогам п.6.1) | B12: =7*'5.Численность персонала'!F20+5*'5.Численность персонала'!B24+8*'5.Численность персонала'!B23+20*'5.Численность персонала'!B25 -> 315
A13: Дополнительная площадь, м2 (Sдоп=ЧпΣ/2*4) | B13: ='5.Численность персонала'!B26/2*4 -> 286
A14: ИТОГО общая площадь Sобщ, м2 | B14: ='4.Табл5_ОборудПлощади'!B11+'4.Табл5_ОборудПлощади'!B12+'4.Табл5_ОборудПлощади'!B13 -> 1141

Sheet 5.Численность персонала
A1: Расчёт численности основных и вспомогательных рабочих (п.6.1)
A3: Операция № | B3: Наименование | C3: Числитель Σ(Qj*tij) | D3: Квн | E3: Чосн расч.=Числ/(Фп*Квн) | F3: Чосн принято
A4: 1 | B4: Станочная | C4: ='4.Табл5_ОборудПлощади'!E4 -> 21250 | D4: 1.03 | E4: =C4/('3.Табл.6 ФондВремени'!D14*D4) -> 11.5645 | F4: =ROUND(E4,0) -> 12
A5: 2 | B5: Слесарная | C5: ='4.Табл5_ОборудПлощади'!E5 -> 26990 | D5: 1 | E5: =C5/('3.Табл.6 ФондВремени'!D14*D5) -> 15.128924 | F5: =ROUND(E5,0) -> 15
A6: 3 | B6: Монтажно-сборочная | C6: ='4.Табл5_ОборудПлощади'!E6 -> 47750 | D6: 1 | E6: =C6/('3.Табл.6 ФондВремени'!D14*D6) -> 26.765695 | F6: =ROUND(E6,0) -> 27
A7: 4 | B7: Наладочная | C7: ='4.Табл5_ОборудПлощади'!E7 -> 78510 | D7: 1 | E7: =C7/('3.Табл.6 ФондВремени'!D14*D7) -> 44.007848 | F7: =ROUND(E7,0) -> 44
A8: 5 | B8: Контролёры (форм.9, принято из л.4) | F8: ='4.Табл5_ОборудПлощади'!H8 -> 3
B9: ИТОГО основных рабочих | F9: =SUM(F4:F8) -> 101
A11: Вспомогательные рабочие (табл.7)
A12: № | B12: Профессия | C12: Норма на 1 осн.раб. | D12: Разряд | E12: Расчётная числ. | F12: Принято (не менее 2)
A13: 1 | B13: Наладчик оборудования | C13: 0.03 | D13: 5 | E13: =C13*'5.Численность персонала'!F9 -> 3.03 | F13: =MAX(2,ROUND(E13,0)) -> 3
A14: 2 | B14: Техник по обслуживанию ПТО | C14: 0.01 | D14: 4 | E14: =C14*'5.Численность персонала'!F9 -> 1.01 | F14: =MAX(2,ROUND(E14,0)) -> 2
A15: 3 | B15: Слесари по ремонту инструмента и приспособлений | C15: 0.015 | D15: 5 | E15: =C15*'5.Численность персонала'!F9 -> 1.515 | F15: =MAX(2,ROUND(E15,0)) -> 2
A16: 4 | B16: Водитель транспортных средств | C16: 0.02 | D16: 4 | E16: =C16*'5.Численность персонала'!F9 -> 2.02 | F16: =MAX(2,ROUND(E16,0)) -> 2
A17: 5 | B17: Разнорабочий (складские/трансп.работы) | C17: 0.02 | D17: 3 | E17: =C17*'5.Численность персонала'!F9 -> 2.02 | F17: =MAX(2,ROUND(E17,0)) -> 2
A18: 6 | B18: Кладовщик инструментального склада | C18: 0.014 | D18: 3 | E18: =C18*'5.Численность персонала'!F9 -> 1.414 | F18: =MAX(2,ROUND(E18,0)) -> 2
A19: 7 | B19: Кладовщик склада готовой продукции | C19: 0.012 | D19: 3 | E19: =C19*'5.Численность персонала'!F9 -> 1.212 | F19: =MAX(2,ROUND(E19,0)) -> 2
B20: ИТОГО вспомогательных рабочих | F20: =SUM(F13:F19) -> 15
A22: Всего рабочих (осн.+всп.) | B22: ='5.Численность персонала'!F9+'5.Численность персонала'!F20 -> 116
A23: Специалисты =MAX(10; 8% от раб.) | B23: =MAX(10,ROUND(0.08*B22,0)) -> 10
A24: Другие служащие =MAX(11; 11% от (раб+спец)) | B24: =MAX(11,ROUND(0.11*(B22+B23),0)) -> 14
A25: Руководители =MAX(2; 2% от (раб+спец+служ)) | B25: =MAX(2,ROUND(0.02*(B22+B23+B24),0)) -> 3
A26: ИТОГО персонал предприятия ЧпΣ | B26: =B22+B23+B24+B25 -> 143

Sheet 6.Табл8-9_Тарифы
A1: Таблица 8 — Тарифная сетка (8 разрядов)
A3: ='1.Исходные данные'!B4/175 -> 154.81714
A5: Разряд | B5: 1 | C5: 2 | D5: 3 | E5: 4 | F5: 5 | G5: 6 | H5: 7 | I5: 8
A6: Кт | B6: 1 | C6: 1.24 | D6: 1.45 | E6: 1.62 | F6: 1.76 | G6: 1.9 | H6: 2.15 | I6: 2.39
A7: Тчk,р. | B7: =ROUND('6.Табл8-9_Тарифы'!A3*B6,2) -> 154.82 | C7: =ROUND('6.Табл8-9_Тарифы'!A3*C6,2) -> 191.97 | D7: =ROUND('6.Табл8-9_Тарифы'!A3*D6,2) -> 224.48 | E7: =ROUND('6.Табл8-9_Тарифы'!A3*E6,2) -> 250.8 | F7: =ROUND('6.Табл8-9_Тарифы'!A3*F6,2) -> 272.48 | G7: =ROUND('6.Табл8-9_Тарифы'!A3*G6,2) -> 294.15 | H7: =ROUND('6.Табл8-9_Тарифы'!A3*H6,2) -> 332.86 | I7: =ROUND('6.Табл8-9_Тарифы'!A3*I6,2) -> 370.01
A9: Таблица 9 — Шкала квалификационных уровней
A10: Ур. | B10: 1 | C10: 2 | D10: 3 | E10: 4 | F10: 5 | G10: 6 | H10: 7 | I10: 8 | J10: 9 | K10: 10 | L10: 11 | M10: 12 | N10: 13 | O10: 14 | P10: 15 | Q10: 16
A11: Коэфф. | B11: 1 | C11: 1.36 | D11: 1.59 | E11: 1.73 | F11: 1.82 | G11: 2 | H11: 2.27 | I11: 2.54 | J11: 2.91 | K11: 3.27 | L11: 3.68 | M11: 4.18 | N11: 4.73 | O11: 5.32 | P11: 5.56 | Q11: 5.95

Sheet 7.Приложение1-2_Штат
A1: Приложение 1 — Штатное расписание руководителей, специалистов, других служащих
A3: Категория | B3: Должность | C3: Кол-во, чел. | D3: Квалиф.уровень | E3: Оклад, р. =МРОТ*коэфф.ур.
A4: Руководители | B4: Директор | C4: 1 | D4: 16 | E4: =ROUND('1.Исходные данные'!B4*'6.Табл8-9_Тарифы'!Q11,2) -> 161203.35
A5: Руководители | B5: Зам. директора | C5: 1 | D5: 14 | E5: =ROUND('1.Исходные данные'!B4*'6.Табл8-9_Тарифы'!O11,2) -> 144134.76
A6: Руководители | B6: Гл. бухгалтер | C6: 1 | D6: 13 | E6: =ROUND('1.Исходные данные'!B4*'6.Табл8-9_Тарифы'!N11,2) -> 128149.89
A7: Специалисты | B7: Технолог | C7: 1 | D7: 10 | E7: =ROUND('1.Исходные данные'!B4*'6.Табл8-9_Тарифы'!K11,2) -> 88594.11
A8: Специалисты | B8: Конструктор | C8: 1 | D8: 10 | E8: =ROUND('1.Исходные данные'!B4*'6.Табл8-9_Тарифы'!K11,2) -> 88594.11
A9: Специалисты | B9: Программист | C9: 1 | D9: 8 | E9: =ROUND('1.Исходные данные'!B4*'6.Табл8-9_Тарифы'!I11,2) -> 68816.22
A10: Специалисты | B10: Бухгалтер | C10: 1 | D10: 8 | E10: =ROUND('1.Исходные данные'!B4*'6.Табл8-9_Тарифы'!I11,2) -> 68816.22
A11: Специалисты | B11: Энергетик | C11: 1 | D11: 9 | E11: =ROUND('1.Исходные данные'!B4*'6.Табл8-9_Тарифы'!J11,2) -> 78840.63
A12: Специалисты | B12: Мастер | C12: 2 | D12: 9 | E12: =ROUND('1.Исходные данные'!B4*'6.Табл8-9_Тарифы'!J11,2) -> 78840.63
A13: Специалисты | B13: Механик | C13: 1 | D13: 9 | E13: =ROUND('1.Исходные данные'!B4*'6.Табл8-9_Тарифы'!J11,2) -> 78840.63
A14: Специалисты | B14: Маркетолог | C14: 1 | D14: 10 | E14: =ROUND('1.Исходные данные'!B4*'6.Табл8-9_Тарифы'!K11,2) -> 88594.11
A15: Специалисты | B15: Экономист | C15: 1 | D15: 10 | E15: =ROUND('1.Исходные данные'!B4*'6.Табл8-9_Тарифы'!K11,2) -> 88594.11
A16: Другие служащие | B16: Агент по снабжению | C16: 1 | D16: 7 | E16: =ROUND('1.Исходные данные'!B4*'6.Табл8-9_Тарифы'!H11,2) -> 61501.11
A17: Другие служащие | B17: Референт | C17: 1 | D17: 7 | E17: =ROUND('1.Исходные данные'!B4*'6.Табл8-9_Тарифы'!H11,2) -> 61501.11
A18: Другие служащие | B18: Экспедитор | C18: 3 | D18: 6 | E18: =ROUND('1.Исходные данные'!B4*'6.Табл8-9_Тарифы'!G11,2) -> 54186
A19: Другие служащие | B19: Инспектор отдела кадров | C19: 1 | D19: 5 | E19: =ROUND('1.Исходные данные'!B4*'6.Табл8-9_Тарифы'!F11,2) -> 49309.26
A20: Другие служащие | B20: Уборщик производственных помещений | C20: 4 | D20: 3 | E20: =ROUND('1.Исходные данные'!B4*'6.Табл8-9_Тарифы'!D11,2) -> 43077.87
A21: Другие служащие | B21: Уборщик бытовых помещений | C21: 4 | D21: 2 | E21: =ROUND('1.Исходные данные'!B4*'6.Табл8-9_Тарифы'!C11,2) -> 36846.48
A23: Проверка: сумма руководителей | C23: =SUMIF(A4:A21,"Руководители",C4:C21) -> 3
A24: Проверка: сумма специалистов | C24: =SUMIF(A4:A21,"Специалисты",C4:C21) -> 10
A25: Проверка: сумма других служащих | C25: =SUMIF(A4:A21,"Другие служащие",C4:C21) -> 14

Sheet 8.КапЗатраты(п.3)
A1: Раздел 3 — Капитальные (единовременные) затраты
A3: Статья затрат | B3: Кратность МРОТ / формула | C3: Значение, р.
A4: Подготовка учредит.документов (ПУД) = Зу*МРОТ, Зу=4 | C4: =4*'1.Исходные данные'!B4 -> 108372
A5: Гос.регистрация предприятия (ГРП) = Зр*МРОТ, Зр=5 | C5: =5*'1.Исходные данные'!B4 -> 135465
A6: Прочие затраты на регистрацию (ПЗ) = Зпр*МРОТ, Зпр=5 | C6: =5*'1.Исходные данные'!B4 -> 135465
A7: Станочное оборудование (Зо) = Цо*Сп.с*МРОТ, Цо=1800 | C7: =1800*'4.Табл5_ОборудПлощади'!H4*'1.Исходные данные'!B4 -> 292604400
A8: Оборудование оп.2 (слесарное) = Цп*Ср2*МРОТ, Цп=500 | C8: =500*'4.Табл5_ОборудПлощади'!H5*'1.Исходные данные'!B4 -> 94825500
A9: Оборудование оп.3 (монтажно-сборочное) | C9: =500*'4.Табл5_ОборудПлощади'!H6*'1.Исходные данные'!B4 -> 162558000
A10: Оборудование оп.4 (наладочное) | C10: =500*'4.Табл5_ОборудПлощади'!H7*'1.Исходные данные'!B4 -> 270930000
A11: Оборудование оп.5 (контроль техпроцессов) | C11: =500*'4.Табл5_ОборудПлощади'!H8*'1.Исходные данные'!B4 -> 40639500
A12: Производственный и хоз.инвентарь (ЗПХИ) = 750*МРОТ | C12: =750*'1.Исходные данные'!B4 -> 20319750
A13: Транспортные средства (ЗТРС) = 1300*МРОТ | C13: =1300*'1.Исходные данные'!B4 -> 35220900
A14: Компьютеры и оргтехника (ЗКТ) = 350*МРОТ | C14: =350*'1.Исходные данные'!B4 -> 9482550
A15: Здания (ЗЗД) = Sобщ*Спл*МРОТ, Спл=15 | C15: =15*'4.Табл5_ОборудПлощади'!B14*'1.Исходные данные'!B4 -> 463696695
A17: ИТОГО капитальные затраты КЗ | C17: =SUM(C4:C15) -> 1390656597

Sheet 9.Прил3_ФОТ_осн.раб
A1: Приложение 3 — Расчёт ФОТ основных рабочих
A3: Опер.№ | B3: Разряд | C3: Тчk,р. | D3: Qа*tА | E3: ЗПсд.А | F3: Qб*tБ | G3: ЗПсд.Б | H3: ЗПсд.Итого | I3: ДОС(35%) | J3: ЗПосн | K3: ЗПдоп(ДЗП) | L3: ФОТ
A4: 1 | B4: 4 | C4: ='6.Табл8-9_Тарифы'!E7 -> 250.8 | D4: ='2.Табл.2 Техпроцесс'!D2 -> 1.8 | E4: ='1.Исходные данные'!B6*D4*C4*'1.Исходные данные'!B13 -> 4232250 | F4: ='2.Табл.2 Техпроцесс'!E2 -> 2.5 | G4: ='1.Исходные данные'!B8*F4*C4*'1.Исходные данные'!B13 -> 2429625 | H4: =E4+G4 -> 6661875 | I4: =0.35*H4 -> 2331656.2 | J4: =H4+I4 -> 8993531.2 | K4: ='1.Исходные данные'!B5*J4 -> 1349029.7 | L4: =J4+K4 -> 10342561
A5: 2 | B5: 4 | C5: ='6.Табл8-9_Тарифы'!E7 -> 250.8 | D5: ='2.Табл.2 Техпроцесс'!D3 -> 2.4 | E5: ='1.Исходные данные'!B6*D5*C5*'1.Исходные данные'!B13 -> 5643000 | F5: ='2.Табл.2 Техпроцесс'!E3 -> 2.9 | G5: ='1.Исходные данные'!B8*F5*C5*'1.Исходные данные'!B13 -> 2818365 | H5: =E5+G5 -> 8461365 | I5: =0.35*H5 -> 2961477.8 | J5: =H5+I5 -> 11422843 | K5: ='1.Исходные данные'!B5*J5 -> 1713426.4 | L5: =J5+K5 -> 13136269
A6: 3 | B6: 3 | C6: ='6.Табл8-9_Тарифы'!D7 -> 224.48 | D6: ='2.Табл.2 Техпроцесс'!D4 -> 4.3 | E6: ='1.Исходные данные'!B6*D6*C6*'1.Исходные данные'!B13 -> 9049350 | F6: ='2.Табл.2 Техпроцесс'!E4 -> 5 | G6: ='1.Исходные данные'!B8*F6*C6*'1.Исходные данные'!B13 -> 4349300 | H6: =E6+G6 -> 13398650 | I6: =0.35*H6 -> 4689527.5 | J6: =H6+I6 -> 18088178 | K6: ='1.Исходные данные'!B5*J6 -> 2713226.6 | L6: =J6+K6 -> 20801404
A7: 4 | B7: 5 | C7: ='6.Табл8-9_Тарифы'!F7 -> 272.48 | D7: ='2.Табл.2 Техпроцесс'!D5 -> 6.5 | E7: ='1.Исходные данные'!B6*D7*C7*'1.Исходные данные'!B13 -> 16604250 | F7: ='2.Табл.2 Техпроцесс'!E5 -> 9.6 | G7: ='1.Исходные данные'!B8*F7*C7*'1.Исходные данные'!B13 -> 10136256 | H7: =E7+G7 -> 26740506 | I7: =0.35*H7 -> 9359177.1 | J7: =H7+I7 -> 36099683 | K7: ='1.Исходные данные'!B5*J7 -> 5414952.5 | L7: =J7+K7 -> 41514636
A8: 5 | B8: 3 | C8: ='6.Табл8-9_Тарифы'!D7 -> 224.48 | D8: ='2.Табл.2 Техпроцесс'!D6 -> 0.5 | E8: ='1.Исходные данные'!B6*D8*C8*'1.Исходные данные'!B13 -> 1052250 | F8: ='2.Табл.2 Техпроцесс'!E6 -> 0.6 | G8: ='1.Исходные данные'!B8*F8*C8*'1.Исходные данные'!B13 -> 521916 | H8: =E8+G8 -> 1574166 | I8: =0.35*H8 -> 550958.1 | J8: =H8+I8 -> 2125124.1 | K8: ='1.Исходные данные'!B5*J8 -> 318768.61 | L8: =J8+K8 -> 2443892.7
H9: ИТОГО ФОТ осн.раб. | L9: =SUM(L4:L8) -> 88238763
A11: Раздельно по изделиям (для табл.13 себестоимости)
A12: Опер.№ | B12: ЗПсд.А | C12: ДОС.А | D12: ЗПосн.А | E12: ЗПдоп.А | F12: ЗПсд.Б | G12: ДОС.Б | H12: ЗПосн.Б | I12: ЗПдоп.Б
A13: 1 | B13: =E4 -> 4232250 | C13: =0.35*B13 -> 1481287.5 | D13: =B13+C13 -> 5713537.5 | E13: ='1.Исходные данные'!B5*D13 -> 857030.62 | F13: =G4 -> 2429625 | G13: =0.35*F13 -> 850368.75 | H13: =F13+G13 -> 3279993.8 | I13: ='1.Исходные данные'!B5*H13 -> 491999.06
A14: 2 | B14: =E5 -> 5643000 | C14: =0.35*B14 -> 1975050 | D14: =B14+C14 -> 7618050 | E14: ='1.Исходные данные'!B5*D14 -> 1142707.5 | F14: =G5 -> 2818365 | G14: =0.35*F14 -> 986427.75 | H14: =F14+G14 -> 3804792.8 | I14: ='1.Исходные данные'!B5*H14 -> 570718.91
A15: 3 | B15: =E6 -> 9049350 | C15: =0.35*B15 -> 3167272.5 | D15: =B15+C15 -> 12216622 | E15: ='1.Исходные данные'!B5*D15 -> 1832493.4 | F15: =G6 -> 4349300 | G15: =0.35*F15 -> 1522255 | H15: =F15+G15 -> 5871555 | I15: ='1.Исходные данные'!B5*H15 -> 880733.25
A16: 4 | B16: =E7 -> 16604250 | C16: =0.35*B16 -> 5811487.5 | D16: =B16+C16 -> 22415738 | E16: ='1.Исходные данные'!B5*D16 -> 3362360.6 | F16: =G7 -> 10136256 | G16: =0.35*F16 -> 3547689.6 | H16: =F16+G16 -> 13683946 | I16: ='1.Исходные данные'!B5*H16 -> 2052591.8
A17: 5 | B17: =E8 -> 1052250 | C17: =0.35*B17 -> 368287.5 | D17: =B17+C17 -> 1420537.5 | E17: ='1.Исходные данные'!B5*D17 -> 213080.62 | F17: =G8 -> 521916 | G17: =0.35*F17 -> 182670.6 | H17: =F17+G17 -> 704586.6 | I17: ='1.Исходные данные'!B5*H17 -> 105687.99
A18: ИТОГО | D18: =SUM(D13:D17) -> 49384485 | E18: =SUM(E13:E17) -> 7407672.8 | H18: =SUM(H13:H17) -> 27344874 | I18: =SUM(I13:I17) -> 4101731.1

Sheet 10.Прил4_ФОТ_всп.раб
A1: Приложение 4 — Расчёт ФОТ вспомогательных рабочих
A3: Профессия | B3: Разряд | C3: Тчk,р. | D3: Числ.,чел | E3: ЗПпр.повр.=Тчk*Фп*Ч*Кр | F3: ДОС(35%) | G3: ЗПосн | H3: ЗПдоп(ДЗП) | I3: ФОТ
A4: Наладчик оборудования | B4: 5 | C4: ='6.Табл8-9_Тарифы'!F7 -> 272.48 | D4: ='5.Численность персонала'!F13 -> 3 | E4: =C4*'3.Табл.6 ФондВремени'!D14*D4*'1.Исходные данные'!B13 -> 1822891.2 | F4: =0.35*E4 -> 638011.92 | G4: =E4+F4 -> 2460903.1 | H4: ='1.Исходные данные'!B5*G4 -> 369135.47 | I4: =G4+H4 -> 2830038.6
A5: Техник по обслуживанию ПТО | B5: 4 | C5: ='6.Табл8-9_Тарифы'!E7 -> 250.8 | D5: ='5.Численность персонала'!F14 -> 2 | E5: =C5*'3.Табл.6 ФондВремени'!D14*D5*'1.Исходные данные'!B13 -> 1118568 | F5: =0.35*E5 -> 391498.8 | G5: =E5+F5 -> 1510066.8 | H5: ='1.Исходные данные'!B5*G5 -> 226510.02 | I5: =G5+H5 -> 1736576.8
A6: Слесари по ремонту инструмента и приспособлений | B6: 5 | C6: ='6.Табл8-9_Тарифы'!F7 -> 272.48 | D6: ='5.Численность персонала'!F15 -> 2 | E6: =C6*'3.Табл.6 ФондВремени'!D14*D6*'1.Исходные данные'!B13 -> 1215260.8 | F6: =0.35*E6 -> 425341.28 | G6: =E6+F6 -> 1640602.1 | H6: ='1.Исходные данные'!B5*G6 -> 246090.31 | I6: =G6+H6 -> 1886692.4
A7: Водитель транспортных средств | B7: 4 | C7: ='6.Табл8-9_Тарифы'!E7 -> 250.8 | D7: ='5.Численность персонала'!F16 -> 2 | E7: =C7*'3.Табл.6 ФондВремени'!D14*D7*'1.Исходные данные'!B13 -> 1118568 | F7: =0.35*E7 -> 391498.8 | G7: =E7+F7 -> 1510066.8 | H7: ='1.Исходные данные'!B5*G7 -> 226510.02 | I7: =G7+H7 -> 1736576.8
A8: Разнорабочий (складские/трансп.работы) | B8: 3 | C8: ='6.Табл8-9_Тарифы'!D7 -> 224.48 | D8: ='5.Численность персонала'!F17 -> 2 | E8: =C8*'3.Табл.6 ФондВремени'!D14*D8*'1.Исходные данные'!B13 -> 1001180.8 | F8: =0.35*E8 -> 350413.28 | G8: =E8+F8 -> 1351594.1 | H8: ='1.Исходные данные'!B5*G8 -> 202739.11 | I8: =G8+H8 -> 1554333.2
A9: Кладовщик инструментального склада | B9: 3 | C9: ='6.Табл8-9_Тарифы'!D7 -> 224.48 | D9: ='5.Численность персонала'!F18 -> 2 | E9: =C9*'3.Табл.6 ФондВремени'!D14*D9*'1.Исходные данные'!B13 -> 1001180.8 | F9: =0.35*E9 -> 350413.28 | G9: =E9+F9 -> 1351594.1 | H9: ='1.Исходные данные'!B5*G9 -> 202739.11 | I9: =G9+H9 -> 1554333.2
A10: Кладовщик склада готовой продукции | B10: 3 | C10: ='6.Табл8-9_Тарифы'!D7 -> 224.48 | D10: ='5.Численность персонала'!F19 -> 2 | E10: =C10*'3.Табл.6 ФондВремени'!D14*D10*'1.Исходные данные'!B13 -> 1001180.8 | F10: =0.35*E10 -> 350413.28 | G10: =E10+F10 -> 1351594.1 | H10: ='1.Исходные данные'!B5*G10 -> 202739.11 | I10: =G10+H10 -> 1554333.2
A11: ИТОГО | I11: =SUM(I4:I10) -> 12852884

Sheet 11.Прил5_ФОТ_РукСпецСлуж
A1: Приложение 5 — Расчёт ФОТ руководителей, специалистов, других служащих
A3: Категория | B3: Должность | C3: Числ,чел | D3: Оклад,р. | E3: ЗПокл=Оклад*Кр | F3: ДОС(35%) | G3: ЗПосн | H3: ЗПдоп(ДЗП) | I3: ФОТгод=(ЗПосн+ЗПдоп)*Ч*12
A4: Руководители | B4: Директор | C4: ='7.Приложение1-2_Штат'!C4 -> 1 | D4: ='7.Приложение1-2_Штат'!E4 -> 161203.35 | E4: =D4*'1.Исходные данные'!B13 -> 201504.19 | F4: =0.35*E4 -> 70526.466 | G4: =E4+F4 -> 272030.65 | H4: ='1.Исходные данные'!B5*G4 -> 40804.598 | I4: =(G4+H4)*C4*12 -> 3754023
A5: Руководители | B5: Зам. директора | C5: ='7.Приложение1-2_Штат'!C5 -> 1 | D5: ='7.Приложение1-2_Штат'!E5 -> 144134.76 | E5: =D5*'1.Исходные данные'!B13 -> 180168.45 | F5: =0.35*E5 -> 63058.957 | G5: =E5+F5 -> 243227.41 | H5: ='1.Исходные данные'!B5*G5 -> 36484.111 | I5: =(G5+H5)*C5*12 -> 3356538.2
A6: Руководители | B6: Гл. бухгалтер | C6: ='7.Приложение1-2_Штат'!C6 -> 1 | D6: ='7.Приложение1-2_Штат'!E6 -> 128149.89 | E6: =D6*'1.Исходные данные'!B13 -> 160187.36 | F6: =0.35*E6 -> 56065.577 | G6: =E6+F6 -> 216252.94 | H6: ='1.Исходные данные'!B5*G6 -> 32437.941 | I6: =(G6+H6)*C6*12 -> 2984290.6
A7: Специалисты | B7: Технолог | C7: ='7.Приложение1-2_Штат'!C7 -> 1 | D7: ='7.Приложение1-2_Штат'!E7 -> 88594.11 | E7: =D7*'1.Исходные данные'!B13 -> 110742.64 | F7: =0.35*E7 -> 38759.923 | G7: =E7+F7 -> 149502.56 | H7: ='1.Исходные данные'!B5*G7 -> 22425.384 | I7: =(G7+H7)*C7*12 -> 2063135.3
A8: Специалисты | B8: Конструктор | C8: ='7.Приложение1-2_Штат'!C8 -> 1 | D8: ='7.Приложение1-2_Штат'!E8 -> 88594.11 | E8: =D8*'1.Исходные данные'!B13 -> 110742.64 | F8: =0.35*E8 -> 38759.923 | G8: =E8+F8 -> 149502.56 | H8: ='1.Исходные данные'!B5*G8 -> 22425.384 | I8: =(G8+H8)*C8*12 -> 2063135.3
A9: Специалисты | B9: Программист | C9: ='7.Приложение1-2_Штат'!C9 -> 1 | D9: ='7.Приложение1-2_Штат'!E9 -> 68816.22 | E9: =D9*'1.Исходные данные'!B13 -> 86020.275 | F9: =0.35*E9 -> 30107.096 | G9: =E9+F9 -> 116127.37 | H9: ='1.Исходные данные'!B5*G9 -> 17419.106 | I9: =(G9+H9)*C9*12 -> 1602557.7
A10: Специалисты | B10: Бухгалтер | C10: ='7.Приложение1-2_Штат'!C10 -> 1 | D10: ='7.Приложение1-2_Штат'!E10 -> 68816.22 | E10: =D10*'1.Исходные данные'!B13 -> 86020.275 | F10: =0.35*E10 -> 30107.096 | G10: =E10+F10 -> 116127.37 | H10: ='1.Исходные данные'!B5*G10 -> 17419.106 | I10: =(G10+H10)*C10*12 -> 1602557.7
A11: Специалисты | B11: Энергетик | C11: ='7.Приложение1-2_Штат'!C11 -> 1 | D11: ='7.Приложение1-2_Штат'!E11 -> 78840.63 | E11: =D11*'1.Исходные данные'!B13 -> 98550.788 | F11: =0.35*E11 -> 34492.776 | G11: =E11+F11 -> 133043.56 | H11: ='1.Исходные данные'!B5*G11 -> 19956.534 | I11: =(G11+H11)*C11*12 -> 1836001.2
A12: Специалисты | B12: Мастер | C12: ='7.Приложение1-2_Штат'!C12 -> 2 | D12: ='7.Приложение1-2_Штат'!E12 -> 78840.63 | E12: =D12*'1.Исходные данные'!B13 -> 98550.788 | F12: =0.35*E12 -> 34492.776 | G12: =E12+F12 -> 133043.56 | H12: ='1.Исходные данные'!B5*G12 -> 19956.534 | I12: =(G12+H12)*C12*12 -> 3672002.3
A13: Специалисты | B13: Механик | C13: ='7.Приложение1-2_Штат'!C13 -> 1 | D13: ='7.Приложение1-2_Штат'!E13 -> 78840.63 | E13: =D13*'1.Исходные данные'!B13 -> 98550.788 | F13: =0.35*E13 -> 34492.776 | G13: =E13+F13 -> 133043.56 | H13: ='1.Исходные данные'!B5*G13 -> 19956.534 | I13: =(G13+H13)*C13*12 -> 1836001.2
A14: Специалисты | B14: Маркетолог | C14: ='7.Приложение1-2_Штат'!C14 -> 1 | D14: ='7.Приложение1-2_Штат'!E14 -> 88594.11 | E14: =D14*'1.Исходные данные'!B13 -> 110742.64 | F14: =0.35*E14 -> 38759.923 | G14: =E14+F14 -> 149502.56 | H14: ='1.Исходные данные'!B5*G14 -> 22425.384 | I14: =(G14+H14)*C14*12 -> 2063135.3
A15: Специалисты | B15: Экономист | C15: ='7.Приложение1-2_Штат'!C15 -> 1 | D15: ='7.Приложение1-2_Штат'!E15 -> 88594.11 | E15: =D15*'1.Исходные данные'!B13 -> 110742.64 | F15: =0.35*E15 -> 38759.923 | G15: =E15+F15 -> 149502.56 | H15: ='1.Исходные данные'!B5*G15 -> 22425.384 | I15: =(G15+H15)*C15*12 -> 2063135.3
A16: Другие служащие | B16: Агент по снабжению | C16: ='7.Приложение1-2_Штат'!C16 -> 1 | D16: ='7.Приложение1-2_Штат'!E16 -> 61501.11 | E16: =D16*'1.Исходные данные'!B13 -> 76876.387 | F16: =0.35*E16 -> 26906.736 | G16: =E16+F16 -> 103783.12 | H16: ='1.Исходные данные'!B5*G16 -> 15567.468 | I16: =(G16+H16)*C16*12 -> 1432207.1
A17: Другие служащие | B17: Референт | C17: ='7.Приложение1-2_Штат'!C17 -> 1 | D17: ='7.Приложение1-2_Штат'!E17 -> 61501.11 | E17: =D17*'1.Исходные данные'!B13 -> 76876.387 | F17: =0.35*E17 -> 26906.736 | G17: =E17+F17 -> 103783.12 | H17: ='1.Исходные данные'!B5*G17 -> 15567.468 | I17: =(G17+H17)*C17*12 -> 1432207.1
A18: Другие служащие | B18: Экспедитор | C18: ='7.Приложение1-2_Штат'!C18 -> 3 | D18: ='7.Приложение1-2_Штат'!E18 -> 54186 | E18: =D18*'1.Исходные данные'!B13 -> 67732.5 | F18: =0.35*E18 -> 23706.375 | G18: =E18+F18 -> 91438.875 | H18: ='1.Исходные данные'!B5*G18 -> 13715.831 | I18: =(G18+H18)*C18*12 -> 3785569.4
A19: Другие служащие | B19: Инспектор отдела кадров | C19: ='7.Приложение1-2_Штат'!C19 -> 1 | D19: ='7.Приложение1-2_Штат'!E19 -> 49309.26 | E19: =D19*'1.Исходные данные'!B13 -> 61636.575 | F19: =0.35*E19 -> 21572.801 | G19: =E19+F19 -> 83209.376 | H19: ='1.Исходные данные'!B5*G19 -> 12481.406 | I19: =(G19+H19)*C19*12 -> 1148289.4
A20: Другие служащие | B20: Уборщик производственных помещений | C20: ='7.Приложение1-2_Штат'!C20 -> 4 | D20: ='7.Приложение1-2_Штат'!E20 -> 43077.87 | E20: =D20*'1.Исходные данные'!B13 -> 53847.338 | F20: =0.35*E20 -> 18846.568 | G20: =E20+F20 -> 72693.906 | H20: ='1.Исходные данные'!B5*G20 -> 10904.086 | I20: =(G20+H20)*C20*12 -> 4012703.6
A21: Другие служащие | B21: Уборщик бытовых помещений | C21: ='7.Приложение1-2_Штат'!C21 -> 4 | D21: ='7.Приложение1-2_Штат'!E21 -> 36846.48 | E21: =D21*'1.Исходные данные'!B13 -> 46058.1 | F21: =0.35*E21 -> 16120.335 | G21: =E21+F21 -> 62178.435 | H21: ='1.Исходные данные'!B5*G21 -> 9326.7653 | I21: =(G21+H21)*C21*12 -> 3432249.6
A22: ИТОГО | I22: =SUM(I4:I21) -> 44139739
A23: в т.ч. ФОТ Руководителей | I23: =SUMIF(A4:A21,"Руководители",I4:I21) -> 10094852
A24: в т.ч. ФОТ Специалистов | I24: =SUMIF(A4:A21,"Специалисты",I4:I21) -> 18801661
A25: в т.ч. ФОТ Других служащих | I25: =SUMIF(A4:A21,"Другие служащие",I4:I21) -> 15243226

Sheet 12.Прил6_СредняяЗП
A1: Приложение 6 — Средняя заработная плата персонала предприятия
A3: Категория персонала | B3: Годовой ФОТ, р. | C3: Численность, чел. | D3: Среднемес. ЗП, р.=ФОТ/Ч/12
A4: Руководители | B4: ='11.Прил5_ФОТ_РукСпецСлуж'!I23 -> 10094852 | C4: ='5.Численность персонала'!B25 -> 3 | D4: =B4/C4/12 -> 280412.55
A5: Специалисты | B5: ='11.Прил5_ФОТ_РукСпецСлуж'!I24 -> 18801661 | C5: ='5.Численность персонала'!B23 -> 10 | D5: =B5/C5/12 -> 156680.51
A6: Другие служащие | B6: ='11.Прил5_ФОТ_РукСпецСлуж'!I25 -> 15243226 | C6: ='5.Численность персонала'!B24 -> 14 | D6: =B6/C6/12 -> 90733.489
A7: Рабочие, в т.ч.: | B7: ='9.Прил3_ФОТ_осн.раб'!L9+'10.Прил4_ФОТ_всп.раб'!I11 -> 1.0109165e+08 | C7: ='5.Численность персонала'!B22 -> 116 | D7: =B7/C7/12 -> 72623.309
A8: основные | B8: ='9.Прил3_ФОТ_осн.раб'!L9 -> 88238763 | C8: ='5.Численность персонала'!F9 -> 101 | D8: =B8/C8/12 -> 72804.259
A9: вспомогательные | B9: ='10.Прил4_ФОТ_всп.раб'!I11 -> 12852884 | C9: ='5.Численность персонала'!F20 -> 15 | D9: =B9/C9/12 -> 71404.912
A10: ИТОГО по предприятию | B10: ='11.Прил5_ФОТ_РукСпецСлуж'!I23+'11.Прил5_ФОТ_РукСпецСлуж'!I24+'11.Прил5_ФОТ_РукСпецСлуж'!I25+'9.Прил3_ФОТ_осн.раб'!L9+'10.Прил4_ФОТ_всп.раб'!I11 -> 1.4523139e+08 | C10: ='5.Численность персонала'!B26 -> 143 | D10: =B10/C10/12 -> 84633.675

Sheet 13.Табл10_Материалы
A1: Таблица 10 — Расшифровка затрат по статье «Сырьё и материалы»
A3: Изделие | B3: Материал | C3: Ед.изм. | D3: Норма расх. | E3: Цена с НДС,р. | F3: Цена без НДС,р.=Ц/1.22 | G3: Сумма на 1шт,р. | H3: Сумма на всё кол-во,р.
A4: А | B4: М1 | C4: кг | D4: 1.1 | E4: 86 | F4: =ROUND(E4/1.22,2) -> 70.49 | G4: =ROUND(D4*F4,2) -> 77.54 | H4: =ROUND(G4*'1.Исходные данные'!B6,2) -> 581550
A5: А | B5: Д1 | C5: шт | D5: 12 | E5: 57 | F5: =ROUND(E5/1.22,2) -> 46.72 | G5: =ROUND(D5*F5,2) -> 560.64 | H5: =ROUND(G5*'1.Исходные данные'!B6,2) -> 4204800
A6: А | B6: Д2 | C6: шт | D6: 10 | E6: 65 | F6: =ROUND(E6/1.22,2) -> 53.28 | G6: =ROUND(D6*F6,2) -> 532.8 | H6: =ROUND(G6*'1.Исходные данные'!B6,2) -> 3996000
A7: А | B7: Д3 | C7: шт | D7: 15 | E7: 49 | F7: =ROUND(E7/1.22,2) -> 40.16 | G7: =ROUND(D7*F7,2) -> 602.4 | H7: =ROUND(G7*'1.Исходные данные'!B6,2) -> 4518000
B8: ИТОГО материалов на изделие А | G8: =SUM(G4:G7) -> 1773.38 | H8: =SUM(H4:H7) -> 13300350
A10: Б | B10: М2 | C10: кг | D10: 9.6 | E10: 47 | F10: =ROUND(E10/1.22,2) -> 38.52 | G10: =ROUND(D10*F10,2) -> 369.79 | H10: =ROUND(G10*'1.Исходные данные'!B8,2) -> 1146349
A11: Б | B11: М3 | C11: кг | D11: 4.5 | E11: 50 | F11: =ROUND(E11/1.22,2) -> 40.98 | G11: =ROUND(D11*F11,2) -> 184.41 | H11: =ROUND(G11*'1.Исходные данные'!B8,2) -> 571671
A12: Б | B12: Д2 | C12: шт | D12: 8 | E12: 65 | F12: =ROUND(E12/1.22,2) -> 53.28 | G12: =ROUND(D12*F12,2) -> 426.24 | H12: =ROUND(G12*'1.Исходные данные'!B8,2) -> 1321344
A13: Б | B13: Д3 | C13: шт | D13: 6 | E13: 49 | F13: =ROUND(E13/1.22,2) -> 40.16 | G13: =ROUND(D13*F13,2) -> 240.96 | H13: =ROUND(G13*'1.Исходные данные'!B8,2) -> 746976
B14: ИТОГО материалов на изделие Б | G14: =SUM(G10:G13) -> 1221.4 | H14: =SUM(H10:H13) -> 3786340

Sheet 14.Табл12_Амортизация
A1: Таблица 12 — Расчёт амортизационных отчислений
A3: Основные средства | B3: Аморт.группа | C3: Тспи,лет | D3: Фперв,р. | E3: Ао=Фперв/Тспи,р.
A4: Здание | B4: 7 | C4: 18 | D4: ='8.КапЗатраты(п.3)'!C15 -> 463696695 | E4: =D4/C4 -> 25760928
A5: Станочное оборудование | B5: 6 | C5: 12 | D5: ='8.КапЗатраты(п.3)'!C7 -> 292604400 | E5: =D5/C5 -> 24383700
A6: Наладочное/регулир./испытат.оборудование | B6: 5 | C6: 8 | D6: ='8.КапЗатраты(п.3)'!C10 -> 270930000 | E6: =D6/C6 -> 33866250
A7: Оборуд. для контроля техпроцессов | B7: 5 | C7: 8 | D7: ='8.КапЗатраты(п.3)'!C11 -> 40639500 | E7: =D7/C7 -> 5079937.5
A8: Произв. и хоз.инвентарь | B8: 4 | C8: 6 | D8: ='8.КапЗатраты(п.3)'!C12 -> 20319750 | E8: =D8/C8 -> 3386625
A9: Транспортные средства | B9: 3 | C9: 4 | D9: ='8.КапЗатраты(п.3)'!C13 -> 35220900 | E9: =D9/C9 -> 8805225
A10: Слесарное оборудование | B10: 2 | C10: 3 | D10: ='8.КапЗатраты(п.3)'!C8 -> 94825500 | E10: =D10/C10 -> 31608500
A11: Монтажно-сборочное оборудование | B11: 2 | C11: 3 | D11: ='8.КапЗатраты(п.3)'!C9 -> 162558000 | E11: =D11/C11 -> 54186000
A12: Компьютеры и оргтехника | B12: 2 | C12: 3 | D12: ='8.КапЗатраты(п.3)'!C14 -> 9482550 | E12: =D12/C12 -> 3160850
A13: ИТОГО годовая амортизация | E13: =SUM(E4:E12) -> 190238015

Sheet 15.Табл11_Накладные
A1: Таблица 11 — Смета затрат накладных расходов (годовая)
A3: № | B3: Статья расходов | C3: Сумма, р.
A4: 1 | B4: Затраты на оплату труда (ФОТ рук+спец+служ+всп.раб) | C4: ='11.Прил5_ФОТ_РукСпецСлуж'!I23+'11.Прил5_ФОТ_РукСпецСлуж'!I24+'11.Прил5_ФОТ_РукСпецСлуж'!I25+'10.Прил4_ФОТ_всп.раб'!I11 -> 56992624
A5: 2 | B5: Страховые взносы (30% от п.1) | C5: ='1.Исходные данные'!B11*C4 -> 17097787
A6: 3 | B6: Амортизационные отчисления (табл.12) | C6: ='14.Табл12_Амортизация'!E13 -> 190238015
A7: 4 | B7: Прочие расходы (60% от п.1) | C7: =0.6*C4 -> 34195574
A8: 5 | B8: ИТОГО общая сумма накладных расходов | C8: =SUM(C4:C7) -> 2.98524e+08
A9: 6 | B9: База распределения: Осн.ЗП осн.рабочих (все изделия) | C9: ='9.Прил3_ФОТ_осн.раб'!D18+'9.Прил3_ФОТ_осн.раб'!H18 -> 76729359
A10: 7 | B10: Процент накладных расходов =(5:6)*100%, округл. вверх до 2 знаков | C10: =ROUNDUP(C8/C9*100,2) -> 389.07

Sheet 16.Табл13_Себестоимость
A1: Таблица 13 — Калькуляция по изделиям «А» и «Б»
A3: № | B3: Статья калькуляции | C3: А: на 1шт | D3: А: на всё | E3: Б: на 1шт | F3: Б: на всё
A4: 1 | B4: Сырьё и материалы | C4: ='13.Табл10_Материалы'!G8 -> 1773.38 | D4: ='13.Табл10_Материалы'!H8 -> 13300350
A5: 2 | B5: Осн.ЗП осн.рабочих | C5: =D5/'1.Исходные данные'!B6 -> 6584.598 | D5: ='9.Прил3_ФОТ_осн.раб'!D18 -> 49384485
A6: 3 | B6: Доп.ЗП осн.рабочих | C6: =D6/'1.Исходные данные'!B6 -> 987.6897 | D6: ='9.Прил3_ФОТ_осн.раб'!E18 -> 7407672.8
A7: 4 | B7: Страховые взносы (30% от (2+3)) | C7: =D7/'1.Исходные данные'!B6 -> 2271.6863 | D7: ='1.Исходные данные'!B11*(D5+D6) -> 17037647
A8: 5 | B8: Накладные расходы (%НР*ст.2) | C8: =D8/'1.Исходные данные'!B6 -> 25618.695 | D8: ='15.Табл11_Накладные'!C10/100*D5 -> 1.9214022e+08
A9: 6 | B9: Производственная себестоимость (1+2+3+4+5) | C9: =D9/'1.Исходные данные'!B6 -> 37236.049 | D9: =SUM(D4:D8) -> 2.7927037e+08
A10: 7 | B10: Коммерческие расходы (15% от ст.6) | C10: =D10/'1.Исходные данные'!B6 -> 5585.4074 | D10: ='1.Исходные данные'!B17*D9 -> 41890556
A11: 8 | B11: ПОЛНАЯ себестоимость (6+7) | C11: =D11/'1.Исходные данные'!B6 -> 42821.457 | D11: =D9+D10 -> 3.2116093e+08
A13: 1 | B13: Сырьё и материалы | E13: ='13.Табл10_Материалы'!G14 -> 1221.4 | F13: ='13.Табл10_Материалы'!H14 -> 3786340
A14: 2 | B14: Осн.ЗП осн.рабочих | E14: =F14/'1.Исходные данные'!B8 -> 8820.927 | F14: ='9.Прил3_ФОТ_осн.раб'!H18 -> 27344874
A15: 3 | B15: Доп.ЗП осн.рабочих | E15: =F15/'1.Исходные данные'!B8 -> 1323.139 | F15: ='9.Прил3_ФОТ_осн.раб'!I18 -> 4101731.1
A16: 4 | B16: Страховые взносы (30% от (2+3)) | E16: =F16/'1.Исходные данные'!B8 -> 3043.2198 | F16: ='1.Исходные данные'!B11*(F14+F15) -> 9433981.4
A17: 5 | B17: Накладные расходы (%НР*ст.2) | E17: =F17/'1.Исходные данные'!B8 -> 34319.581 | F17: ='15.Табл11_Накладные'!C10/100*F14 -> 1.063907e+08
A18: 6 | B18: Производственная себестоимость (1+2+3+4+5) | E18: =F18/'1.Исходные данные'!B8 -> 48728.267 | F18: =SUM(F13:F17) -> 1.5105763e+08
A19: 7 | B19: Коммерческие расходы (15% от ст.6) | E19: =F19/'1.Исходные данные'!B8 -> 7309.24 | F19: ='1.Исходные данные'!B17*F18 -> 22658644
A20: 8 | B20: ПОЛНАЯ себестоимость (6+7) | E20: =F20/'1.Исходные данные'!B8 -> 56037.507 | F20: =F18+F19 -> 1.7371627e+08

Sheet 17.Цена_ФинРезультаты
A1: Раздел 7.2-7.3 — Цена изделий, точка безубыточности, финансовые результаты
A3: Показатель | B3: Изделие А | C3: Изделие Б
A4: Точка безубыточности K = Q*Пр/365, шт (округл.) | B4: =ROUND('1.Исходные данные'!B6*'1.Исходные данные'!B7/365,0) -> 3699 | C4: =ROUND('1.Исходные данные'!B8*'1.Исходные данные'!B9/365,0) -> 1529
A5: Пост.затраты Зпост=НРвсе+КРвсе, р. | B5: ='16.Табл13_Себестоимость'!D8+'16.Табл13_Себестоимость'!D10 -> 2.3403077e+08 | C5: ='16.Табл13_Себестоимость'!F17+'16.Табл13_Себестоимость'!F19 -> 1.2904934e+08
A6: Перем.затраты на 1шт Зпер.уд (мат+ЗПосн+ЗПдоп+СВ на ед.), р. | B6: ='16.Табл13_Себестоимость'!C4+'16.Табл13_Себестоимость'!C5+'16.Табл13_Себестоимость'!C6+'16.Табл13_Себестоимость'!C7 -> 11617.354 | C6: ='16.Табл13_Себестоимость'!E13+'16.Табл13_Себестоимость'!E14+'16.Табл13_Себестоимость'!E15+'16.Табл13_Себестоимость'!E16 -> 14408.686
A7: Цена Ц = Зпост/K + Зпер.уд, р. (2 знака) | B7: =ROUND('17.Цена_ФинРезультаты'!B5/'17.Цена_ФинРезультаты'!B4+'17.Цена_ФинРезультаты'!B6,2) -> 74886.01 | C7: =ROUND('17.Цена_ФинРезультаты'!C5/'17.Цена_ФинРезультаты'!C4+'17.Цена_ФинРезультаты'!C6,2) -> 98809.83
A8: Проверка: в т.безуб. Себестоимость=Выручка (допуск ~30-45р) | B8: =('17.Цена_ФинРезультаты'!B5+'17.Цена_ФинРезультаты'!B6*'17.Цена_ФинРезультаты'!B4) - ('17.Цена_ФинРезультаты'!B7*'17.Цена_ФинРезультаты'!B4) -> 12.912165 | C8: =('17.Цена_ФинРезультаты'!C5+'17.Цена_ФинРезультаты'!C6*'17.Цена_ФинРезультаты'!C4) - ('17.Цена_ФинРезультаты'!C7*'17.Цена_ФинРезультаты'!C4) -> -5.3349115
A10: Финансовые результаты (табл.14)
A11: Показатель | B11: А | C11: Б | D11: По предприятию
A12: Выручка от продажи В=Ц*Q, р. | B12: ='17.Цена_ФинРезультаты'!B7*'1.Исходные данные'!B6 -> 561645075 | C12: ='17.Цена_ФинРезультаты'!C7*'1.Исходные данные'!B8 -> 306310473 | D12: =B12+C12 -> 867955548
A13: Переменные затраты на объём=Зпер.уд*Q, р. | B13: ='17.Цена_ФинРезультаты'!B6*'1.Исходные данные'!B6 -> 87130155 | C13: ='17.Цена_ФинРезультаты'!C6*'1.Исходные данные'!B8 -> 44666926 | D13: =B13+C13 -> 1.3179708e+08
A14: Маржинальная прибыль Пмарж=В-Зпер, р. | B14: =B12-B13 -> 4.7451492e+08 | C14: =C12-C13 -> 2.6164355e+08 | D14: =B14+C14 -> 7.3615847e+08
A15: Постоянные затраты на объём, р. | B15: ='17.Цена_ФинРезультаты'!B5 -> 2.3403077e+08 | C15: ='17.Цена_ФинРезультаты'!C5 -> 1.2904934e+08 | D15: =B15+C15 -> 3.6308012e+08
A16: Прибыль от продаж Ппрод=Пмарж-Зпост, р. | B16: =B14-B15 -> 2.4048415e+08 | C16: =C14-C15 -> 1.325942e+08 | D16: =B16+C16 -> 3.7307835e+08
A17: Налог на прибыль НП=25%*Ппрод, р. | B17: ='1.Исходные данные'!B12*B16 -> 60121037 | C17: ='1.Исходные данные'!B12*C16 -> 33148551 | D17: =B17+C17 -> 93269588
A18: Чистая прибыль Пчист=Ппрод-НП, р. | B18: =B16-B17 -> 1.8036311e+08 | C18: =C16-C17 -> 99445652 | D18: =B18+C18 -> 2.7980876e+08
A19: Рентабельность продукции Rпрод=Ппрод/(Зпост+Зпер)*100,% (3 знака) | B19: =ROUND(B16/(B15+B13)*100,3) -> 74.88 | C19: =ROUND(C16/(C15+C13)*100,3) -> 76.328 | D19: =ROUND(D16/(D15+D13)*100,3) -> 75.388
A20: Рентабельность продаж Rпродаж=Ппрод/В*100,% (3 знака) | B20: =ROUND(B16/B12*100,3) -> 42.818 | C20: =ROUND(C16/C12*100,3) -> 43.288 | D20: =ROUND(D16/D12*100,3) -> 42.984

Sheet 18.Табл15_График
A1: Таблица 15 — Данные для построения графика безубыточности
A3: Изделие | B3: Q,шт | C3: Зпер.уд | D3: ЗперΣ=Зпер.уд*Q | E3: ЗпостΣ | F3: SполΣ=ЗперΣ+ЗпостΣ | G3: Цуд | H3: В=Цуд*Q
A4: А | B4: 0 | C4: ='17.Цена_ФинРезультаты'!B6 -> 11617.354 | D4: =C4*(0) -> 0 | E4: ='17.Цена_ФинРезультаты'!B5 -> 2.3403077e+08 | F4: =D4+E4 -> 2.3403077e+08 | G4: ='17.Цена_ФинРезультаты'!B7 -> 74886.01 | H4: =G4*(0) -> 0
A5: А | B5: К_А (т.безуб.) | C5: ='17.Цена_ФинРезультаты'!B6 -> 11617.354 | D5: =C5*('17.Цена_ФинРезультаты'!B4) -> 42972592 | E5: ='17.Цена_ФинРезультаты'!B5 -> 2.3403077e+08 | F5: =D5+E5 -> 2.7700336e+08 | G5: ='17.Цена_ФинРезультаты'!B7 -> 74886.01 | H5: =G5*('17.Цена_ФинРезультаты'!B4) -> 2.7700335e+08
A6: А | B6: Q_А (годовой) | C6: ='17.Цена_ФинРезультаты'!B6 -> 11617.354 | D6: =C6*('1.Исходные данные'!B6) -> 87130155 | E6: ='17.Цена_ФинРезультаты'!B5 -> 2.3403077e+08 | F6: =D6+E6 -> 3.2116093e+08 | G6: ='17.Цена_ФинРезультаты'!B7 -> 74886.01 | H6: =G6*('1.Исходные данные'!B6) -> 561645075
A7: Б | B7: 0 | C7: ='17.Цена_ФинРезультаты'!C6 -> 14408.686 | D7: =C7*(0) -> 0 | E7: ='17.Цена_ФинРезультаты'!C5 -> 1.2904934e+08 | F7: =D7+E7 -> 1.2904934e+08 | G7: ='17.Цена_ФинРезультаты'!C7 -> 98809.83 | H7: =G7*(0) -> 0
A8: Б | B8: К_Б (т.безуб.) | C8: ='17.Цена_ФинРезультаты'!C6 -> 14408.686 | D8: =C8*('17.Цена_ФинРезультаты'!C4) -> 22030881 | E8: ='17.Цена_ФинРезультаты'!C5 -> 1.2904934e+08 | F8: =D8+E8 -> 1.5108022e+08 | G8: ='17.Цена_ФинРезультаты'!C7 -> 98809.83 | H8: =G8*('17.Цена_ФинРезультаты'!C4) -> 1.5108023e+08
A9: Б | B9: Q_Б (годовой) | C9: ='17.Цена_ФинРезультаты'!C6 -> 14408.686 | D9: =C9*('1.Исходные данные'!B8) -> 44666926 | E9: ='17.Цена_ФинРезультаты'!C5 -> 1.2904934e+08 | F9: =D9+E9 -> 1.7371627e+08 | G9: ='17.Цена_ФинРезультаты'!C7 -> 98809.83 | H9: =G9*('1.Исходные данные'!B8) -> 306310473

Sheet 19.Табл16_Итоги
A1: Таблица 16 — Показатели деятельности предприятия
A3: № | B3: Наименование показателя | C3: Ед.изм. | D3: Результат
A4: 1 | B4: Капитальные (единовременные) затраты | C4: р. | D4: ='8.КапЗатраты(п.3)'!C17 -> 1390656597
A5: 2 | B5: Общая площадь | C5: м2 | D5: ='4.Табл5_ОборудПлощади'!B14 -> 1141
A6: 3 | B6: Численность работников предприятия, всего | C6: чел. | D6: ='5.Численность персонала'!B26 -> 143
A7: 3.1 | B7: в т.ч. рабочих | C7: чел. | D7: ='5.Численность персонала'!B22 -> 116
A8: 3.2 | B8: руководителей | C8: чел. | D8: ='5.Численность персонала'!B25 -> 3
A9: 3.3 | B9: специалистов | C9: чел. | D9: ='5.Численность персонала'!B23 -> 10
A10: 3.4 | B10: других служащих | C10: чел. | D10: ='5.Численность персонала'!B24 -> 14
A11: 4 | B11: ФОТ | C11: р. | D11: ='12.Прил6_СредняяЗП'!B10 -> 1.4523139e+08
A12: 5.1 | B12: Себестоимость единицы изделия «А» | C12: р. | D12: ='16.Табл13_Себестоимость'!C11 -> 42821.457
A13: 5.2 | B13: Себестоимость единицы изделия «Б» | C13: р. | D13: ='16.Табл13_Себестоимость'!E20 -> 56037.507
A14: 6.1 | B14: Прогнозируемая цена единицы изделия «А» | C14: р. | D14: ='17.Цена_ФинРезультаты'!B7 -> 74886.01
A15: 6.2 | B15: Прогнозируемая цена единицы изделия «Б» | C15: р. | D15: ='17.Цена_ФинРезультаты'!C7 -> 98809.83
A16: 7 | B16: Выручка от реализации продукции | C16: р. | D16: ='17.Цена_ФинРезультаты'!D12 -> 867955548
A17: 8 | B17: Маржинальный доход (прибыль) | C17: р. | D17: ='17.Цена_ФинРезультаты'!D14 -> 7.3615847e+08
A18: 9 | B18: Прибыль от продаж | C18: р. | D18: ='17.Цена_ФинРезультаты'!D16 -> 3.7307835e+08
A19: 10 | B19: Чистая прибыль | C19: р. | D19: ='17.Цена_ФинРезультаты'!D18 -> 2.7980876e+08
A20: 11 | B20: Рентабельность предприятия (капзатрат) Rкз=Пчист/КЗ*100 | C20: % | D20: =ROUND('17.Цена_ФинРезультаты'!D18/'8.КапЗатраты(п.3)'!C17*100,3) -> 20.121
A21: 12 | B21: Срок окупаемости капитальных затрат Ток=КЗ/Пчист | C21: лет | D21: =ROUND('8.КапЗатраты(п.3)'!C17/'17.Цена_ФинРезультаты'!D18,2) -> 4.97
A23: Вывод: | B23: =IF(D21<=7,"Срок окупаемости не более 5-7 лет — проект создания предприятия ЭФФЕКТИВЕН","Срок окупаемости превышает 7 лет — проект НЕэффективен") -> Срок окупаемости не более 5-7 лет — проект создания предприятия ЭФФЕКТИВЕН
